exchango/__init__.py
exchango/async_api/__init__.py
exchango/async_api/_utils.py
exchango/sync_api/__init__.py
exchango/sync_api/_utils.py
exchango-1.0.2.dist-info/METADATA
exchango-1.0.2.dist-info/WHEEL
exchango-1.0.2.dist-info/top_level.txt
exchango-1.0.2.dist-info/RECORD
