Metadata-Version: 2.4
Name: exchango
Version: 1.0.2
Summary: Exchango - modern Python library for obtaining current exchange rates and converting currencies with support for both synchronous and asynchronous interfaces. Easy integration, flexible settings, and regular data updates.
Home-page: 
Author: zvenios
Author-email: kont.05.vladdd@gmail.com
Keywords: currency,exchange,converter,forex,rates,synchronous,asynchronous,async,sync,aiohttp,requests,conversion,money,finance,financial,api,exchangerate,currency-converter,toolkit
Classifier: Programming Language :: Python :: 3
Classifier: Programming Language :: Python :: 3.7
Classifier: Programming Language :: Python :: 3.8
Classifier: Programming Language :: Python :: 3.9
Classifier: Programming Language :: Python :: 3.10
Classifier: Programming Language :: Python :: 3.11
Classifier: License :: OSI Approved :: MIT License
Classifier: Operating System :: OS Independent
Classifier: Intended Audience :: Developers
Classifier: Intended Audience :: Financial and Insurance Industry
Classifier: Topic :: Office/Business :: Financial
Classifier: Topic :: Software Development :: Libraries :: Python Modules
Requires-Python: >=3.7
Requires-Dist: requests>=2.25.1
Requires-Dist: aiohttp>=3.8.1
Requires-Dist: async_lru>=2.0.4
Requires-Dist: pytz>=2021.3
Provides-Extra: dev
Requires-Dist: pytest>=6.2.5; extra == "dev"
Requires-Dist: pytest-asyncio>=0.15.1; extra == "dev"
Requires-Dist: coverage>=5.5; extra == "dev"
Requires-Dist: sphinx>=4.0.2; extra == "dev"
Provides-Extra: speed
Requires-Dist: uvloop>=0.16.0; platform_system != "Windows" and extra == "speed"
Dynamic: author
Dynamic: author-email
Dynamic: classifier
Dynamic: description
Dynamic: description-content-type
Dynamic: keywords
Dynamic: provides-extra
Dynamic: requires-dist
Dynamic: requires-python
Dynamic: summary
